{
  "city": "Pasir Gunung Selatan",
  "latitude": -6.3594,
  "longitude": 106.8461,
  "temperature_celsius": 26.37,
  "condition": "Clouds",
  "condition_description": "few clouds",
  "icon_code": "02n",
  "temp_min_celsius": 25.71,
  "temp_max_celsius": 27.75,
  "humidity": 71,
  "feels_like_celsius": 26.37,
  "pressure": 1011,
  "visibility": 10000,
  "wind_deg": 250,
  "gust_speed": ,
  "wind_speed": 2.06,
  "rainfall_mm": ,
  "snowfall_mm": ,
  "clouds": 20,
  "sunrise_readable": "2025-11-24 05:26:17",
  "sunset_readable": "2025-11-24 17:52:34",
  "timezone": 25200,
  "coord_lon": 106.8461,
  "coord_lat": -6.3594,
  "wind_direction_text": "West-Southwest",
  "weather_description_with_wind": "Wind Direction: West-Southwest",
  "forecast_24h": [          {
            "temperature_celsius": 26.37,
            "condition": "Clouds",
            "icon_code": "02n",
            "date_readable": "01:00"
          },          {
            "temperature_celsius": 26.64,
            "condition": "Clouds",
            "icon_code": "03n",
            "date_readable": "04:00"
          },          {
            "temperature_celsius": 27.86,
            "condition": "Clouds",
            "icon_code": "04d",
            "date_readable": "07:00"
          },          {
            "temperature_celsius": 32.30,
            "condition": "Clouds",
            "icon_code": "04d",
            "date_readable": "10:00"
          },          {
            "temperature_celsius": 34.57,
            "condition": "Clouds",
            "icon_code": "04d",
            "date_readable": "13:00"
          },          {
            "temperature_celsius": 33.41,
            "condition": "Clouds",
            "icon_code": "04d",
            "date_readable": "16:00"
          },          {
            "temperature_celsius": 29.96,
            "condition": "Clouds",
            "icon_code": "04n",
            "date_readable": "19:00"
          },          {
            "temperature_celsius": 28.58,
            "condition": "Clouds",
            "icon_code": "04n",
            "date_readable": "22:00"
          },
  ]
}

